RotamerConvolveMD-1.3.2.data/scripts/convolve-mtss-rotamers.py
RotamerConvolveMD-1.3.2.data/scripts/convolve-mtss-rotamers_pre.py
rotcon/__init__.py
rotcon/_version.py
rotcon/convolve.py
rotcon/convolve_pre.py
rotcon/library.py
rotcon/data/R1A_298K_populations_2011.dat
rotcon/data/R1A_298K_populations_2015.dat
rotcon/data/rotamer1_R1A_298K_2011.dcd
rotcon/data/rotamer1_R1A_298K_2011.pdb
rotcon/data/rotamer1_R1A_298K_2015.dcd
rotcon/data/rotamer1_R1A_298K_2015.pdb
RotamerConvolveMD-1.3.2.dist-info/AUTHORS
RotamerConvolveMD-1.3.2.dist-info/AUTHORS~
RotamerConvolveMD-1.3.2.dist-info/LICENSE
RotamerConvolveMD-1.3.2.dist-info/METADATA
RotamerConvolveMD-1.3.2.dist-info/WHEEL
RotamerConvolveMD-1.3.2.dist-info/top_level.txt
RotamerConvolveMD-1.3.2.dist-info/zip-safe
RotamerConvolveMD-1.3.2.dist-info/RECORD
