Metadata-Version: 2.1
Name: RotamerConvolveMD
Version: 1.3.2
Summary: Analysis of spin label distances over structural ensembles
Home-page: https://github.com/MDAnalysis/RotamerConvolveMD
Author: Philip W. Fowler
Author-email: philip.fowler@ndm.ox.ac.uk
License: GPL 2
Project-URL: Documentation, https://www.mdanalysis.org/RotamerConvolveMD
Project-URL: Source, https://github.com/MDAnalysis/RotamerConvolveMD
Project-URL: Issue Tracker, https://github.com/MDAnalysis/RotamerConvolveMD/issues/
Project-URL: Mailing list, https://groups.google.com/group/mdnalysis-discussion
Keywords: science proteins
Platform: UNKNOWN
Classifier: Development Status :: 7 - Inactive
Classifier: Environment :: Console
Classifier: Intended Audience :: Science/Research
Classifier: License :: OSI Approved :: GNU General Public License v2 (GPLv2)
Classifier: Programming Language :: Python
Classifier: Programming Language :: Python :: 2
Classifier: Programming Language :: Python :: 2.7
Classifier: Programming Language :: Python :: 3
Classifier: Programming Language :: Python :: 3.4
Classifier: Programming Language :: Python :: 3.5
Classifier: Programming Language :: Python :: 3.6
Classifier: Topic :: Scientific/Engineering
Classifier: Topic :: Scientific/Engineering :: Bio-Informatics
Classifier: Topic :: Scientific/Engineering :: Chemistry
Requires: numpy (>=1.6)
Requires: MDAnalysis (>=0.16.2)
Provides: rotcon
Requires-Dist: numpy (>=1.6.0)
Requires-Dist: MDAnalysis (>=0.16.2)
